bugx/README.md
bugx/__about__.py
bugx/__init__.py
bugx/__main__.py
bugx/bugreport_extractor.py
bugx/cli.py
bugx/cli_constants.py
bugx/updater.py
bugx/utils.py
bugx/watcher.py
bugx-0.1.9.dist-info/METADATA
bugx-0.1.9.dist-info/WHEEL
bugx-0.1.9.dist-info/entry_points.txt
bugx-0.1.9.dist-info/RECORD
