Metadata-Version: 2.4
Name: bugx
Version: 0.1.9
Summary: Bug Report extractor
Author-email: Govardhan Ummadisetty <vardhank9@gmail.com>
Requires-Python: >=3.12
Requires-Dist: flagsmith>=3.8.0
Requires-Dist: inquirerpy>=0.3.4
Requires-Dist: prettytable>=3.15.1
Requires-Dist: typer>=0.15.2
Requires-Dist: watchdog>=6.0.0
